ocio_lut_prescription/__init__.py
ocio_lut_prescription/__main__.py
ocio_lut_prescription/core/__init__.py
ocio_lut_prescription/core/ocio.py
ocio_lut_prescription/core/ui.py
ocio_lut_prescription/ui/__init__.py
ocio_lut_prescription/ui/main_window.ui
ocio_lut_prescription/ui/qrc.py
ocio_lut_prescription/ui/resource.qrc
ocio_lut_prescription-1.2.0.dist-info/LICENSE
ocio_lut_prescription-1.2.0.dist-info/METADATA
ocio_lut_prescription-1.2.0.dist-info/WHEEL
ocio_lut_prescription-1.2.0.dist-info/entry_points.txt
ocio_lut_prescription-1.2.0.dist-info/top_level.txt
ocio_lut_prescription-1.2.0.dist-info/RECORD
