Metadata-Version: 2.1
Name: ocio-lut-prescription
Version: 1.2.0
Summary: GUI wrapper of ociobakelut command.
Home-page: https://github.com/djieff/ocio-lut-prescription
Author: Jean-Francois Bouchard
Author-email: bouchard.jfrancois@gmail.com
License: MIT license
Keywords: ocio-lut-prescription
Classifier: Development Status :: 5 - Production/Stable
Classifier: Intended Audience :: End Users/Desktop
Classifier: Intended Audience :: Science/Research
Classifier: Intended Audience :: Telecommunications Industry
Classifier: License :: OSI Approved :: MIT License
Classifier: Natural Language :: English
Classifier: Programming Language :: Python :: 3.8
Classifier: Topic :: Artistic Software
Classifier: Topic :: Multimedia :: Graphics :: Graphics Conversion
Classifier: Topic :: Multimedia :: Video :: Conversion
Classifier: Topic :: Scientific/Engineering :: Image Processing
Requires-Python: >=3.8
License-File: LICENSE
Requires-Dist: PySide2
Requires-Dist: opencolorio (>=2)
